protein_turnover/__init__.py
protein_turnover/__main__.py
protein_turnover/algo.py
protein_turnover/api.py
protein_turnover/background.py
protein_turnover/background_ui.py
protein_turnover/broken_api.py
protein_turnover/cli.py
protein_turnover/config.py
protein_turnover/current_fit.py
protein_turnover/dec2023_fit.py
protein_turnover/exts.py
protein_turnover/filters.py
protein_turnover/fitenvelopes.py
protein_turnover/jobs.py
protein_turnover/logger.py
protein_turnover/mailer.py
protein_turnover/parallel_utils.py
protein_turnover/pepxml.py
protein_turnover/pepxml_reader.py
protein_turnover/plotting.py
protein_turnover/protxml.py
protein_turnover/py.typed
protein_turnover/pymz.py
protein_turnover/pymz_ui.py
protein_turnover/resourcefiles.py
protein_turnover/settings.py
protein_turnover/sns.py
protein_turnover/unimod.py
protein_turnover/utils.py
protein_turnover/view.py
protein_turnover/web.py
protein_turnover/web_ui.py
protein_turnover/website.py
protein_turnover/dinosaur/__init__.py
protein_turnover/dinosaur/cmd.py
protein_turnover/dinosaur/dinosaur.py
protein_turnover/sqla/__init__.py
protein_turnover/sqla/iso_peaks.py
protein_turnover/sqla/iso_peaks_ui.py
protein_turnover/sqla/model.py
protein_turnover/sqla/query.py
protein_turnover/sqla/utils.py
protein_turnover/types/__init__.py
protein_turnover/types/checking.py
protein_turnover/types/mzmltypes.py
protein_turnover/types/numpytypes.py
protein_turnover/types/pepxmltypes.py
protein_turnover/types/turnovertype.py
protein_turnover-0.8.0.dist-info/METADATA
protein_turnover-0.8.0.dist-info/WHEEL
protein_turnover-0.8.0.dist-info/entry_points.txt
protein_turnover-0.8.0.dist-info/licenses/LICENSE
protein_turnover-0.8.0.dist-info/RECORD
