Metadata-Version: 2.4
Name: protein-turnover
Version: 0.8.0
Summary: protein turnover pipeline
Project-URL: Repository, https://github.com/arabidopsis/protein_turnover.git
Author-email: Ian Castleden <ian.castleden@uwa.edu.au>
License-Expression: MIT
License-File: LICENSE
Classifier: Development Status :: 4 - Beta
Classifier: Intended Audience :: Science/Research
Classifier: Programming Language :: Python :: 3 :: Only
Classifier: Topic :: Scientific/Engineering :: Bio-Informatics
Requires-Python: >=3.12
Requires-Dist: click<9,>=8.1.3
Requires-Dist: lxml<7,>=6.0.0
Requires-Dist: matplotlib<4,>=3.10.0
Requires-Dist: more-itertools<11,>=10.6.0
Requires-Dist: pandas<3,>=2.3.0
Requires-Dist: pyarrow<22,>=19.0.0
Requires-Dist: pymzml<3,>=2.5.11
Requires-Dist: pyteomics<5,>=4.5.3
Requires-Dist: scipy<2,>=1.15
Requires-Dist: sqlalchemy<3,>=2.0.20
Requires-Dist: tomli-w<2,>=1.2.0
Requires-Dist: typing-extensions<5,>=4.12.2
Provides-Extra: all
Requires-Dist: psutil<8,>=7.0; extra == 'all'
Requires-Dist: unidecode<2,>=1.3.8; extra == 'all'
Provides-Extra: psutil
Requires-Dist: psutil<8,>=7.0; extra == 'psutil'
Provides-Extra: unidecode
Requires-Dist: unidecode<2,>=1.3.8; extra == 'unidecode'
